{
  "red031000": {
    "Discord": "red031000#2155",
    "Steam": "id/red031000",
    "Twitch": "red031000",
    "GitHub": "red031000",
    "Twitter": "red031000",
    "Reddit": "red031000"
  },
  "S.": {
    "Discord": "S.#3003",
    "Steam": "id/LotsOfS",
    "YouTube": "lotsofs",
    "Twitch": "lotsofs",
    "GitHub": "lotsofs",
    "Twitter": "lotsofs"
  },
  "samfundev": {
    "Discord": "samfundev#8972",
    "Steam": "id/samfundev",
    "GitHub": "samfundev",
    "Reddit": "samfundev"
  },
  "Timwi": {
    "Discord": "Timwi#0551",
    "Steam": "id/timwi",
    "GitHub": "Timwi",
    "Reddit": "Timwi",
    "Twitch": "timwiterby",
    "YouTube": "UCDc_zmPDwDAH_6WuXUkdVIw"
  }
}
