{
  "Compatibility": "Compatible",
  "Contributors": {
    "Developer": [ "Sean Obach" ],
    "Manual": [ "Pruz" ],
    "Twitch Plays": [
      "eXish",
      "Sean Obach"
    ]
  },
  "DefuserDifficulty": "Easy",
  "Description": "Take the number and colors from the display and perform calculations on it until the value becomes 0. Tags: 12-buttons, keypad, display, 9-digit-number, colors",
  "ExpertDifficulty": "Medium",
  "ModuleID": "0",
  "Name": "0",
  "Origin": "Mods",
  "Published": "2020-07-16",
  "SortKey": "0",
  "SourceUrl": "https://github.com/obachs971/0pruz",
  "Souvenir": {
    "Explanation": "Souvenir could ask about the initially displayed number.",
    "Status": "Considered"
  },
  "SteamID": "2168041338",
  "Symbol": "0",
  "TutorialVideos": [ {
    "Language": "English",
    "Url": "https://www.youtube.com/watch?v=RfkP-E-HP0o"
  } ],
  "Type": "Regular"
}