{
  "Compatibility": "Compatible",
  "Contributors": {
    "Developer": [ "That one kid" ],
    "Twitch Plays": [ "eXish" ]
  },
  "DefuserDifficulty": "Medium",
  "Description": "Figure out the right time to press a button again, and again, and again... Tags: button, 2-displays, exclamation-mark, gray-background",
  "ExpertDifficulty": "Hard",
  "ModuleID": "repeatAgain",
  "MysteryModule": "MustNotBeHidden",
  "Name": "Again",
  "Origin": "Mods",
  "Published": "2022-02-22",
  "Quirks": "WillSolveSuddenly, PseudoNeedy, TimeDependent",
  "SortKey": "AGAIN",
  "SourceUrl": "https://github.com/Kbushra/ktaneRepeatAgain",
  "SteamID": "2761754312",
  "Symbol": "Agn",
  "TutorialVideos": [ {
    "Language": "English",
    "Url": "https://www.youtube.com/watch?v=tBEKap0_bVw"
  } ],
  "Type": "Regular"
}