{
  "Compatibility": "Compatible",
  "Contributors": { "Developer": [ "Timwi" ] },
  "DefuserDifficulty": "VeryEasy",
  "Description": "Construct a Huffman tree from fake character scores, then decode a word from its Huffman encoding. Tags: blue-background, cipher, 3-screens, left, right, keyboard",
  "ExpertDifficulty": "VeryHard",
  "ModuleID": "BlueHuffmanCipherModule",
  "Name": "Blue Huffman Cipher",
  "Origin": "Mods",
  "Published": "2021-09-19",
  "SortKey": "BLUEHUFFMANCIPHER",
  "SourceUrl": "https://github.com/Timwi/KtaneCompressionCiphers",
  "Souvenir": {
    "Explanation": "Souvenir could ask about the encoded word (last screen on page 2).",
    "Status": "Considered"
  },
  "SteamID": "2604427370",
  "Symbol": "Bhc",
  "TutorialVideos": [ {
    "Language": "English",
    "Url": "https://youtu.be/LxuDhyneneo?t=922"
  } ],
  "Type": "Regular"
}