{
  "Author": "GhostSalt",
  "Compatibility": "Compatible",
  "DefuserDifficulty": "Medium",
  "Description": "Activate a series of bumpers, based on their colours and LED states and the bomb's serial number. Tags: black-background, pinball, bumpers, LEDs, colours, 6-stages",
  "ExpertDifficulty": "Hard",
  "ModuleID": "GSBumpers",
  "Name": "Bumpers",
  "Origin": "Mods",
  "Published": "2025-08-07",
  "SortKey": "BUMPERS",
  "SourceUrl": "https://github.com/GhostSalt/Bumpers",
  "Souvenir": {
    "Explanation": "Souvenir could ask about the lit bumpers on any given stage.",
    "Status": "Considered"
  },
  "SteamID": "3544150616",
  "Symbol": "Bum",
  "Type": "Regular"
}