{
    "Author": "EternityShack",
    "Compatibility": "Compatible",
    "DefuserDifficulty": "Medium",
    "Descriptions": [
      {
        "Description": "Input a combination of red, green and blue to solve the module.",
        "Language": "English",
        "Tags": "hash, pound, 6-0s, 3-squares, 3-rectangles"
      },
      {
        "Description": "Entrer une combinaison de rouge, de vert et de bleu pour désamorcer le module.",
        "Language": "Français",
        "Tags": "dièse, 3-carrés, trois-carrés, 3-rectangles, trois-rectangles"
      }
    ],
    "ExpertDifficulty": "Medium",
    "ModuleID": "Color Generator",
    "Name": "Color Generator",
    "Origin": "Mods",
    "Published": "2017-09-24",
    "SortKey": "COLORGENERATOR",
    "SourceUrl": "https://github.com/EternityShack/KTANE_ColorGenerator",
    "Souvenir": { "Status": "NotACandidate" },
    "SteamID": "1145222040",
    "Symbol": "Cog",
    "TutorialVideos": [
      {
        "Language": "Čeština",
        "Url": "https://www.youtube.com/watch?v=budAfsaB_3Y"
      },
      {
        "Language": "English",
        "Url": "https://www.youtube.com/watch?v=gxA6LZkhJlI"
      }
    ],
    "Type": "Regular"
  }