{
  "Compatibility": "Compatible",
  "Contributors": {
    "Developer": [ "TracksJosh" ],
    "Modeling": [ "UnrulyJuli3" ]
  },
  "DefuserDifficulty": "Hard",
  "Description": "Answer a random tossup from an online repository of tossups to solve the module. Tags: 2-button, screen, big-button, tossup, typing, connection-symbol, history, literature, science, fine arts.",
  "ExpertDifficulty": "VeryEasy",
  "ModuleID": "connectedQuizbowl",
  "Name": "Connected Quizbowl",
  "Origin": "Mods",
  "Published": "2025-04-01",
  "SortKey": "CONNECTEDQUIZBOWL",
  "SourceUrl": "https://github.com/TracksJosh/ktaneConnectedQuizbowl-master",
  "SteamID": "3455986959",
  "Symbol": "Coqu",
  "Type": "Regular"
}