{
  "Compatibility": "Compatible",
  "Contributors": {
    "Developer": [ "Theta" ],
    "Twitch Plays": [ "eXish" ]
  },
  "DefuserDifficulty": "Easy",
  "Description": "Boolean Maze except more NOT fun. Now with wraparound! Tags: red, logic, move, 6-buttons, display, stuck, reset",
  "ExpertDifficulty": "Hard",
  "ModuleID": "boolMazeCruel",
  "Name": "Cruel Boolean Maze",
  "Origin": "Mods",
  "Published": "2019-11-11",
  "SortKey": "CRUELBOOLEANMAZE",
  "SourceUrl": "https://github.com/davidcpayette/Cruel-Boolean-Maze",
  "Souvenir": { "Status": "NotACandidate" },
  "SteamID": "1911110811",
  "Symbol": "Cbmz",
  "TutorialVideos": [ {
    "Language": "English",
    "Url": "https://www.youtube.com/watch?v=lrwYskhchKo"
  } ],
  "Type": "Regular"
}