{
  "Author": "Marksam",
  "Compatibility": "Compatible",
  "DefuserDifficulty": "Hard",
  "Description": "Press the four buttons in the correct order throughout 3 stages to disarm the module. Tags: red-module, keypads, seven-segment-display",
  "ExpertDifficulty": "Hard",
  "ModuleID": "CruelKeypads",
  "MysteryModule": "MustNotBeHidden",
  "Name": "Cruel Keypads",
  "Origin": "Mods",
  "Published": "2019-12-29",
  "SortKey": "CRUELKEYPAD",
  "SourceUrl": "https://github.com/marksam32/ktaneCruelKeypads",
  "Souvenir": {
    "Explanation": "Souvenir could ask about the color of the strip for every stage and the symbols in every stage.",
    "Status": "Considered"
  },
  "SteamID": "1950736574",
  "Symbol": "Ckp",
  "TutorialVideoUrl": { "default": "https://www.youtube.com/watch?v=-ByFidUB5Zo" },
  "Type": "Regular"
}