{
  "Author": "Obvious",
  "Compatibility": "Compatible",
  "DefuserDifficulty": "Easy",
  "Description": "Determine the initial setup that led to the shown diffusion. Tags: black-background",
  "ExpertDifficulty": "Trivial",
  "ModuleID": "diffusion",
  "Name": "Diffusion",
  "Origin": "Mods",
  "Published": "2021-02-16",
  "SortKey": "DIFFUSION",
  "SourceUrl": "https://github.com/Ob3vious/KTaNE_Diffusion",
  "SteamID": "2398091842",
  "Symbol": "Dfn",
  "TutorialVideos": [ {
    "Language": "English",
    "Url": "https://www.youtube.com/watch?v=RD_GYETzUyU"
  } ],
  "Type": "Regular"
}