{
  "Author": "Kritzy",
  "Compatibility": "Compatible",
  "DefuserDifficulty": "Hard",
  "Description": "Make a correct bet, find the correct card and send the money you won to a (fake) card number. Tags: Four, Card, Bet, send, money",
  "ExpertDifficulty": "Hard",
  "Ignore": [
    "Cookie Jars",
    "Cruel Purgatory",
    "Divided Squares",
    "Encryption Bingo",
    "Forget Enigma",
    "Forget Everything",
    "Forget Me Later",
    "Forget Me Not",
    "Forget Perspective",
    "Forget Them All",
    "Forget This",
    "Forget Us Not",
    "Four-Card Monte",
    "Hogwarts",
    "Organization",
    "Purgatory",
    "Simon's Stages",
    "Souvenir",
    "Tallordered Keys",
    "The Swan",
    "The Time Keeper",
    "The Troll",
    "Timing is Everything",
    "Turn The Key",
    "The Very Annoying Button",
    "Ultimate Custom Night",
    "Übermodule"
  ],
  "ModuleID": "Krit4CardMonte",
  "Name": "Four-Card Monte",
  "Origin": "Mods",
  "Published": "2019-03-24",
  "SortKey": "FOURCARDMONTE",
  "SourceUrl": "https://github.com/Kritzyy/KTaNE-Four-Card-Monte",
  "Souvenir": {
    "Explanation": "Souvenir could ask about the cards and coins.",
    "Status": "Considered"
  },
  "SteamID": "1691902955",
  "Symbol": "Fc",
  "TwitchPlays": { "Score": 11 },
  "Type": "Regular"
}