{
  "Author": "Blananas2",
  "Compatibility": "Compatible",
  "DefuserDifficulty": "VeryEasy",
  "Description": "Calculate the directions in which the 4 Pac-Man ghosts move. Tags: 5-circles, 5-screens, 5-buttons",
  "ExpertDifficulty": "Medium",
  "ModuleID": "ghostMovement",
  "Name": "Ghost Movement",
  "Origin": "Mods",
  "Published": "2021-02-18",
  "SortKey": "GHOSTMOVEMENT",
  "SourceUrl": "https://github.com/Blananas2/ktane-ghostMovement",
  "SteamID": "2400323193",
  "Symbol": "Gmm",
  "TutorialVideos": [ {
    "Language": "English",
    "Url": "https://www.youtube.com/watch?v=6tajFd6kZQA"
  } ],
  "Type": "Regular"
}