{
  "Author": "Timwi",
  "Compatibility": "Compatible",
  "DefuserDifficulty": "Easy",
  "Description": "Navigate out of this hexagonal maze. Find the correct maze by matching up provided markings, but the maze may be rotated. Tags: 4-hexagon-sides, 7-hexagons-wide",
  "ExpertDifficulty": "Hard",
  "ModuleID": "HexamazeModule",
  "Name": "Hexamaze",
  "Origin": "Mods",
  "Published": "2016-11-21",
  "RuleSeedSupport": "Supported",
  "SortKey": "HEXAMAZE",
  "SourceUrl": "https://github.com/Timwi/KtaneHexamaze",
  "Souvenir": { "Status": "Supported" },
  "SteamID": "803924558",
  "Symbol": "Hmz",
  "TutorialVideos": [
    {
      "Language": "Čeština",
      "Url": "https://www.youtube.com/watch?v=Br1NqhxY8r8"
    },
    {
      "Language": "English",
      "Url": "https://www.youtube.com/watch?v=GRbsyUesG7E"
    },
    {
      "Language": "Français",
      "Url": "https://www.youtube.com/watch?v=_XIRjBkORR4"
    }
  ],
  "Type": "Regular"
}