{
  "Author": "Timwi, Mickeylover, JαmεςH",
  "Compatibility": "Compatible",
  "DefuserDifficulty": "Hard",
  "Description": "Solve other modules on the bomb for each of the Houses of Hogwarts. The calculate their point scores and determine which House wins the House Cup. Tags: banner, module name, parchment, scroll, Gryffindor, Hufflepuff, Ravenclaw, Slytherin",
  "ExpertDifficulty": "Medium",
  "ModuleID": "HogwartsModule",
  "Name": "Hogwarts",
  "Origin": "Mods",
  "Published": "2018-12-29",
  "SortKey": "HOGWARTS",
  "SourceUrl": "https://github.com/Timwi/KtaneHogwarts",
  "Souvenir": {
    "Explanation": "Souvenir could ask which module was solved for which House and/or how many points each House earned.",
    "Status": "Considered"
  },
  "SteamID": "1607221836",
  "Symbol": "Hg",
  "TwitchPlaysSupport": "NotSupported",
  "Type": "Regular"
}