{
  "Author": "SKiPP, LeGeND, ZekNikZ, reupload by Timwi",
  "Compatibility": "Compatible",
  "DefuserDifficulty": "Easy",
  "Description": "Sell the appropriate flavors of ice cream while avoiding triggering your customers’ allergies. Tags: name, left-arrow, right-arrow, sell",
  "ExpertDifficulty": "Medium",
  "ModuleID": "iceCreamModule",
  "Name": "Ice Cream",
  "Origin": "Mods",
  "Published": "2017-06-26",
  "SortKey": "ICECREAM",
  "SourceUrl": "https://github.com/Timwi/KtaneIceCream",
  "Souvenir": { "Status": "Supported" },
  "SteamID": "1649217354",
  "Symbol": "Ic",
  "TutorialVideoUrl": "https://www.youtube.com/watch?v=aNqGcnPbYXg",
  "Type": "Regular"
}