{
  "Contributors": {
    "Audio": [ "Crazycaleb" ],
    "Developer": [
      "Blananas2",
      "Quinn Wuest"
    ],
    "Maintainer": [ "Crazycaleb" ],
    "Manual": [ "Crazycaleb" ],
    "Modeling": [ "Crazycaleb" ]
  },
  "DefuserDifficulty": "Easy",
  "Description": "Collect 3 purple squares in a maze where the status of the walls can be determined by rotating the bomb. Tags: maze, 3-purple-squares, 1-yellow-square, walls, arrows, event-secret-santa-2",
  "ExpertDifficulty": "Trivial",
  "ModuleID": "LenticularMaze",
  "Name": "Lenticular Maze",
  "Origin": "Mods",
  "Published": "2025-12-14",
  "SortKey": "LENTICULAR MAZE",
  "SourceUrl": "https://github.com/Crazycaleb/LenticularMaze",
  "SteamID": "3624034190",
  "Symbol": "Lcm",
  "Type": "Regular"
}