{
  "Author": "ManiaMate",
  "Compatibility": "Compatible",
  "DefuserDifficulty": "Medium",
  "Description": "Find out which mii you are looking at over a range of 100 choices from your old classic Wii! Tags: miis, keyboard, identification",
  "ExpertDifficulty": "Medium",
  "ModuleID": "miiIdentification",
  "Name": "Mii Identification",
  "Origin": "Mods",
  "Published": "2021-01-10",
  "SortKey": "MIIIDENTIFICATION",
  "SourceUrl": "https://github.com/ManiaMate/KTANEMiiIdentification",
  "Souvenir": {
    "Explanation": "Souvenir could ask about the displayed Mii.",
    "Status": "Considered"
  },
  "SteamID": "2358100059",
  "Symbol": "Mii",
  "TutorialVideos": [ {
    "Language": "English",
    "Url": "https://www.youtube.com/watch?v=PJYokhGbAt8"
  } ],
  "Type": "Regular"
}