{
  "Author": "Deaf",
  "Compatibility": "Compatible",
  "DefuserDifficulty": "VeryHard",
  "Description": "Punch Deez Nuts!!! Tags: status-light, 4-buttons, labels",
  "ExpertDifficulty": "VeryHard",
  "ModuleID": "NeeDeez Nuts",
  "MysteryModule": "MustNotBeHiddenOrKey",
  "Name": "NeeDeez Nuts",
  "Origin": "Mods",
  "Published": "2020-06-02",
  "SortKey": "NEEDEEZNUTS",
  "SourceUrl": "https://github.com/Fartlicker777/NeeDeez-Nuts",
  "Souvenir": { "Status": "NotACandidate" },
  "SteamID": "2117154468",
  "Type": "Needy"
 }