{
  "Compatibility": "Compatible",
  "Contributors": {
    "Developer": [ "Deaf" ],
    "Modeling": [ "eXish" ]
  },
  "DefuserDifficulty": "VeryEasy",
  "Description": "Determine if you cut the next wire in a sequence of wires based on the one previously cut. Tags: black-background, yellow-button, one-wire, display",
  "ExpertDifficulty": "Easy",
  "ModuleID": "NextInLine",
  "Name": "Next In Line",
  "Origin": "Mods",
  "Published": "2021-01-14",
  "SortKey": "NEXTINLINE",
  "SourceUrl": "https://github.com/Fartlicker777/Next-In-Line",
  "Souvenir": {
    "Explanation": "Souvenir could ask what the color of the first wire was.",
    "Status": "Considered"
  },
  "SteamID": "2361619770",
  "Symbol": "Nil",
  "TutorialVideos": [ {
    "Language": "English",
    "Url": "https://youtu.be/088bPL29zCE?t=105"
  } ],
  "Type": "Regular"
}