{
	"Author": "Kusane, Andrio Celos",
	"Compatibility": "Untested",
	"DefuserDifficulty": "Easy",
	"Description": "Follow a roller-coaster of rules to press the correct buttons in this Who's on First lookalike. Tags: 6-buttons, display, words, 5-lights",
	"ExpertDifficulty": "Hard",
	"ModuleID": "NotWhosOnFirst",
	"Name": "Not Who's on First",
	"Origin": "Mods",
	"Published": "2020-03-06",
	"SortKey": "NOTWHOSONFIRST",
	"SourceUrl": "https://github.com/AndrioCelos/KtaneNotVanillaModules",
	"Souvenir": {
		"Explanation": "Souvenir could ask about the labels and positions of the buttons pressed in each stage, and the final sum in stage 2.",
		"Status": "Considered"
	},
	"SteamID": "2003251353",
	"Symbol": "Xf",
	"Type": "Regular"
}
