{
  "Compatibility": "Compatible",
  "Contributors": {
    "Developer": [ "Andrio Celos" ],
    "Manual": [ "Kusane Hexaku" ]
  },
  "DefuserDifficulty": "Easy",
  "Description": "Cut the wires in the correct order to spell a word using the corresponding letters in this Wires lookalike. Tags: 6-wires, horizontal-wires",
  "ExpertDifficulty": "Easy",
  "ModuleID": "NotWiresword",
  "Name": "Not Wiresword",
  "Origin": "Mods",
  "Published": "2020-03-06",
  "SortKey": "NOTWIRESWORD",
  "SourceUrl": "https://github.com/AndrioCelos/KtaneNotVanillaModules/tree/main/Assets/Modules/Not%20Wiresword",
  "Souvenir": { "Status": "NotACandidate" },
  "SteamID": "2003251353",
  "Symbol": "Nw",
  "TutorialVideos": [ {
    "Language": "English",
    "Url": "https://www.youtube.com/watch?v=vYMA1WiMuJs"
  } ],
  "Type": "Regular"
}