{
  "Author": "tandyCake",
  "Compatibility": "Compatible",
  "DefuserDifficulty": "VeryEasy",
  "Description": "Move around a 3x3 grid to each digit in the serial number. Tags: 4-buttons, color-number, numpad",
  "ExpertDifficulty": "VeryEasy",
  "ModuleID": "numpath",
  "Name": "Numpath",
  "Origin": "Mods",
  "Published": "2021-03-12",
  "SortKey": "NUMPATH",
  "SourceUrl": "https://github.com/tandyCake/KTaNENumpath",
  "Souvenir": { "Status": "Supported" },
  "SteamID": "2422986865",
  "Symbol": "Nph",
  "TutorialVideos": [ {
    "Language": "English",
    "Url": "https://www.youtube.com/watch?v=AndnTLV32sQ?t=411"
  } ],
  "Type": "Regular"
}