{
  "Author": "Timwi",
  "Compatibility": "Compatible",
  "DefuserDifficulty": "Medium",
  "Description": "Deduce the location and orientation of symbols on the faces of a cube. Inspired by a puzzle from the Professor Layton puzzle game series. Tags: 11-squares, symbols, cube-net, red-squares, yellow-squares, green-square",
  "ExpertDifficulty": "VeryHard",
  "ModuleID": "PatternCubeModule",
  "Name": "Pattern Cube",
  "Origin": "Mods",
  "Published": "2018-07-28",
  "RuleSeedSupport": "Supported",
  "SortKey": "PATTERNCUBE",
  "SourceUrl": "https://github.com/Timwi/KtanePatternCube",
  "Souvenir": { "Status": "Supported" },
  "SteamID": "1453622997",
  "Symbol": "Pqb",
  "TutorialVideos": [
    {
      "Description": "mental strategy, using Notepad (Timwi)",
      "Language": "English",
      "Url": "https://www.youtube.com/watch?v=6M1-KsMY_80"
    },
    {
      "Description": "physical strategy, using props (Sean Obach)",
      "Language": "English",
      "Url": "https://www.youtube.com/watch?v=tDgn_57yTt0"
    },
    {
      "Description": "visual strategy, using Paint (hallojasper)",
      "Language": "English",
      "Url": "https://www.youtube.com/watch?v=uK_k5Ewx36U"
    }
  ],
  "Type": "Regular"
}