{
  "Author": "BigCrunch22",
  "Compatibility": "Compatible",
  "DefuserDifficulty": "Medium",
  "Description": "Submit the exact name of the plant being shown in the module three times. Tags: plants, mystery, PvZ2, keyboard",
  "ExpertDifficulty": "Hard",
  "ModuleID": "PlantIdentification",
  "Name": "Plant Identification",
  "Origin": "Mods",
  "Published": "2020-05-10",
  "SortKey": "PLANTIDENTIFICATION",
  "SourceUrl": "https://github.com/BigCrunch22/PlantIdentification",
  "SteamID": "2091676029",
  "Symbol": "Pid"
  "Type": "Regular"
}