{
  "Author": "Sean Obach",
  "Compatibility": "Compatible",
  "DefuserDifficulty": "Medium",
  "Description": "A 3 step module using different ciphers. Tags: red, qwerty-keyboard",
  "ExpertDifficulty": "Hard",
  "ModuleID": "redCipher",
  "Name": "Red Cipher",
  "Origin": "Mods",
  "Published": "2019-09-02",
  "SortKey": "REDCIPHER",
  "SourceUrl": "https://github.com/obachs971/RedCipher",
  "Souvenir": {
    "Explanation": "Souvenir could ask about the solution word.",
    "Status": "Considered"
  },
  "SteamID": "1852030206",
  "Symbol": "Rci",
  "TutorialVideoUrl": "https://www.youtube.com/watch?v=Fm4kIt-PbqA",
  "Type": "Regular"
}