{
  "Author": "Royal_Flu$h",
  "Compatibility": "Compatible",
  "DefuserDifficulty": "VeryHard",
  "Description": "Keep track of a number of flashing color sequences across the course of the bomb and submit a new color sequence at the end. Tags: flashing-lights, colors, colours, monochrome, dark, Simon, semicircles, counter",
  "ExpertDifficulty": "VeryHard",
  "Ignore": [
    "Cruel Purgatory",
    "Forget Enigma",
    "Forget Everything",
    "Forget It Not",
    "Forget Me Later",
    "Forget Me Not",
    "Forget Perspective",
    "Forget Them All",
    "Forget This",
    "Forget Us Not",
    "Organization",
    "Purgatory",
    "Simon's Stages",
    "Souvenir",
    "Tallordered Keys",
    "The Swan",
    "The Time Keeper",
    "The Troll",
    "Timing is Everything",
    "Turn The Key",
    "The Very Annoying Button",
    "Ultimate Custom Night",
    "Übermodule"
  ],
  "ModuleID": "simonsStages",
  "Name": "Simon’s Stages",
  "Origin": "Mods",
  "Published": "2019-01-03",
  "SortKey": "SIMONSSTAGES",
  "SourceUrl": "https://github.com/RoyalFlush411/simonsStages",
  "Souvenir": { "Status": "NotACandidate" },
  "SteamID": "1612847920",
  "Symbol": "Za",
  "TutorialVideoUrl": "https://www.youtube.com/watch?v=U3QtwiLOIiU",
  "TwitchPlays": {
    "AutoPin": true,
    "ScorePerModule": 1.5
  },
  "Type": "Regular"
}