{
  "Compatibility": "Compatible",
  "Contributors": {
    "Developer": [ "Berdnne" ],
    "Twitch Plays": [ "Kilo Bites" ]
  },
  "DefuserDifficulty": "Easy",
  "Description": "This module presents you with a soda can and a nutrition facts label. Sip and slurp accordingly to solve the module! Tags: soda, can, pop, food, drink, 2-buttons, sip, slurp, nutrition-facts",
  "ExpertDifficulty": "Easy",
  "ModuleID": "soda",
  "Name": "Soda",
  "Origin": "Mods",
  "Published": "2023-12-29",
  "SortKey": "SODA",
  "SourceUrl": "https://github.com/berdnne/ktane-soda-module",
  "SteamID": "3125525686",
  "Symbol": "Sda",
  "TutorialVideos": [ {
    "Language": "English",
    "Url": "https://www.youtube.com/watch?v=jL0RFTukYEg"
  } ],
  "Type": "Regular"
}