{
  "Compatibility": "Compatible",
  "Contributors": {
    "Developer": [ "TheCrazyCodr" ],
    "Modeling": [ "Panoptes (Xel)" ],
    "Twitch Plays": [ "eXish" ]
  },
  "DefuserDifficulty": "VeryEasy",
  "Description": "This module is a SQL code simulator. To disarm it, produce a SQL query that outputs a given result. Tags: green-electronics-background, goal, check, select, where, limit, skip, 11-buttons",
  "ExpertDifficulty": "Medium",
  "ModuleID": "sqlBasic",
  "Name": "SQL - Basic",
  "Origin": "Mods",
  "Published": "2021-06-19",
  "SortKey": "SQLBASIC",
  "SourceUrl": "https://github.com/crazycodr/ktane-sqlmod",
  "Souvenir": { "Status": "NotACandidate" },
  "SteamID": "2524560073",
  "Symbol": "Sqlb",
  "TutorialVideos": [ {
    "Language": "English",
    "Url": "https://youtu.be/cA9eFyRBowI"
  } ],
  "Type": "Regular"
}