{
  "Author": "Deaf",
  "Compatibility": "Compatible",
  "DefuserDifficulty": "VeryEasy",
  "Description": "Double or nothing: The module. Tags: big sword, pit of wires, wires, wire, rope, wire",
  "ExpertDifficulty": "VeryEasy",
  "ModuleID": "SwordOfDamocles",
  "MysteryModule": "MustNotBeHidden",
  "Name": "Sword of Damocles",
  "Origin": "Mods",
  "Published": "2023-07-15",
  "Quirks": "SolvesBeforeSome, InstantDeath",
  "SortKey": "SWORDOFDAMOCLES",
  "SourceUrl": "https://github.com/Fartlicker777/SwordOfDamocles",
  "Souvenir": { "Status": "NotACandidate" },
  "SteamID": "3004007177",
  "Symbol": "Sod",
  "Type": "Regular"
}