{
  "Compatibility": "Compatible",
  "Contributors": { "Developer": [ "Panoptes (Xel)" ] },
  "DefuserDifficulty": "Easy",
  "Description": "Perform three symmetry operations on a square. Inspired by 3blue1brown's videos on group theory. Tags: squares, black-module, 3blue1brown.",
  "ExpertDifficulty": "VeryEasy",
  "ModuleID": "xelSymmetriesOfASquare",
  "Name": "Symmetries Of A Square",
  "Origin": "Mods",
  "Published": "2020-10-09",
  "SortKey": "SYMMETRIESOFASQUARE",
  "SourceUrl": "https://github.com/Mirage-Xel/xelSymmetriesOfASquare",
  "Souvenir": { "Status": "NotACandidate" },
  "SteamID": "2252514085",
  "Symbol": "Syq",
  "TutorialVideos": [ {
    "Language": "English",
    "Url": "https://www.youtube.com/watch?v=cWKXwUEZkbw?t=26"
  } ],
  "Type": "Regular"
}