{
  "Author": "TheThirdMan",
  "Compatibility": "Compatible",
  "DefuserDifficulty": "Medium",
  "Description": "Select the first valid card in a very strange deck. Tags: 2-buttons, submit-button, deck, cards",
  "ExpertDifficulty": "Medium",
  "ModuleID": "deckOfManyThings",
  "Name": "The Deck of Many Things",
  "Origin": "Mods",
  "Published": "2019-06-29",
  "SortKey": "DECKOFMANYTHINGS",
  "SourceUrl": "https://github.com/luisdiogo98/ktane-deckOfManyThings",
  "Souvenir": { "Status": "Supported" },
  "SteamID": "1785189166",
  "Symbol": "Domt",
  "TutorialVideoUrl": "https://www.youtube.com/watch?v=Jfc2iAKkdBg",
  "Type": "Regular"
}