{
  "Contributors": { "Developer": [ "Obvious" ] },
  "DefuserDifficulty": "Trivial",
  "Description": "Push a button harder. Tags: 1-button, big-button",
  "ExpertDifficulty": "Trivial",
  "ModuleID": "resilientButton",
  "Name": "The Resilient Button",
  "Origin": "Mods",
  "Published": "2026-04-01",
  "SortKey": "RESILIENT BUTTON",
  "SourceUrl": "https://github.com/Ob3vious/KTaNE_TheResilientButton",
  "Souvenir": { "Status": "NotACandidate" },
  "SteamID": "3696726664",
  "Symbol": "Resb",
  "Type": "Regular"
}