{
  "Author": "lingomaniac88",
  "Compatibility": "Compatible",
  "DefuserDifficulty": "Medium",
  "Description": "Play five consecutive hands of video poker using optimal strategy. Tags: cards, game-info, speed, bet-one, bet-max, deal",
  "ExpertDifficulty": "Hard",
  "ModuleID": "videoPoker",
  "Name": "Video Poker",
  "Origin": "Mods",
  "Published": "2020-11-08",
  "SortKey": "VIDEOPOKER",
  "SourceUrl": "https://github.com/lingomaniac88/ktaneVideoPoker",
  "Souvenir": { "Status": "NotACandidate" },
  "SteamID": "2280853251",
  "Symbol": "Vpkr",
  "TutorialVideos": [
    {
      "Description": "BlvdBroken",
      "Language": "English",
      "Url": "https://www.youtube.com/watch?v=bOonnHeTUY0"
    },
    {
      "Description": "Crazycaleb",
      "Language": "English",
      "Url": "https://www.youtube.com/watch?v=oivabuJ1ZkI"
    }
  ],
  "Type": "Regular"
}