{
  "Compatibility": "Compatible",
  "Contributors": {
    "Developer": [ "Sean Obach" ],
    "Twitch Plays": [
      "eXish",
      "Sean Obach"
    ]
  },
  "DefuserDifficulty": "VeryEasy",
  "Description": "A 3 step module using different ciphers. Tags: white, qwerty-keyboard",
  "ExpertDifficulty": "Hard",
  "ModuleID": "whiteCipher",
  "Name": "White Cipher",
  "ObsoleteSteamIDs": [ "1894852193" ],
  "Origin": "Mods",
  "Published": "2019-10-21",
  "SortKey": "WHITECIPHER",
  "SourceUrl": "https://github.com/obachs971/UltimateCipher/",
  "Souvenir": { "Status": "Supported" },
  "SteamID": "1932944041",
  "Symbol": "Wci",
  "TutorialVideos": [ {
    "Language": "English",
    "Url": "https://www.youtube.com/watch?v=Cuj4ra95XNQ"
  } ],
  "Type": "Regular"
}