{
  "Compatibility": "Compatible",
  "Contributors": {
    "Developer": [ "Dragoon" ],
    "Manual": [ "Pruz" ]
  },
  "DefuserDifficulty": "Medium",
  "Description": "Select arrows in a specific order going clockwise or counter-clockwise a table. Tags: display, black, 10 buttons, arrows, clockwise, counter-clockwise",
  "ExpertDifficulty": "Hard",
  "ModuleID": "clockCounter",
  "Name": "↻↺",
  "Origin": "Mods",
  "Published": "2023-09-16",
  "SortKey": "↻↺",
  "SourceUrl": "https://github.com/SegaSaturnity/KtaneClockCounter",
  "SteamID": "3036732817",
  "Symbol": "Clco",
  "Type": "Regular"
}